MANIFEST.in
Makefile
README
setup.cfg
setup.py
test/__init__.py
test/__init__.pyc
test/test_compile.py
test/test_migrate.py
test/__pycache__/test_compile.cpython-27-PYTEST.pyc
test/__pycache__/test_migrate.cpython-27-PYTEST.pyc
tiddlywebplugins/__init__.py
tiddlywebplugins/migrate.py
tiddlywebplugins.migrate.egg-info/PKG-INFO
tiddlywebplugins.migrate.egg-info/SOURCES.txt
tiddlywebplugins.migrate.egg-info/dependency_links.txt
tiddlywebplugins.migrate.egg-info/namespace_packages.txt
tiddlywebplugins.migrate.egg-info/not-zip-safe
tiddlywebplugins.migrate.egg-info/requires.txt
tiddlywebplugins.migrate.egg-info/top_level.txt