Metadata-Version: 1.0
Name: tiddlywebplugins.migrate
Version: 0.8
Summary: Migrate the contents of one tiddlyweb store to another
Home-page: http://pypi.python.org/pypi/tiddlywebplugins.migrate
Author: Chris Dent
Author-email: cdent@peermore.com
License: UNKNOWN
Platform: Posix; MacOS X; Windows
